tap_geo/__init__.py
tap_geo/__main__.py
tap_geo/osm.py
tap_geo/storage.py
tap_geo/streams.py
tap_geo/tap.py
tap_geo-0.1.2.dist-info/METADATA
tap_geo-0.1.2.dist-info/WHEEL
tap_geo-0.1.2.dist-info/entry_points.txt
tap_geo-0.1.2.dist-info/licenses/LICENSE
tap_geo-0.1.2.dist-info/RECORD
