Metadata-Version: 2.4
Name: tap-geo
Version: 0.1.2
Summary: Singer tap for Geo, built with the Meltano Singer SDK.
Author-email: Luca Capra <luca.capra@spindox.it>
License-Expression: Apache-2.0
License-File: LICENSE
Keywords: ELT,Geo
Classifier: Intended Audience :: Developers
Classifier: License :: OSI Approved :: Apache Software License
Classifier: Operating System :: OS Independent
Classifier: Programming Language :: Python :: 3.10
Classifier: Programming Language :: Python :: 3.11
Classifier: Programming Language :: Python :: 3.12
Classifier: Programming Language :: Python :: 3.13
Classifier: Programming Language :: Python :: 3.14
Requires-Python: >=3.10
Requires-Dist: boto3>=1.39.11
Requires-Dist: gpxpy
Requires-Dist: osmium>=4.1.1
Requires-Dist: pyshp
Requires-Dist: s3fs>=2025.9.0
Requires-Dist: shapely>=2.1.1
Requires-Dist: singer-sdk~=0.49.1
Provides-Extra: s3
Requires-Dist: s3fs~=2025.9.0; extra == 's3'
